sandbox/__init__.py
sandbox/box.py
sandbox/challenge.py
sandbox/config.py
little_sandbox_py-1.1.2.dist-info/LICENSE
little_sandbox_py-1.1.2.dist-info/METADATA
little_sandbox_py-1.1.2.dist-info/WHEEL
little_sandbox_py-1.1.2.dist-info/top_level.txt
little_sandbox_py-1.1.2.dist-info/RECORD
