Metadata-Version: 2.1
Name: little-sandbox-py
Version: 1.1.2
Summary: A sandbox for running python scripts
Home-page: https://github.com/Hustcw/Little-Sandbox
Author: hustcw
Author-email: UNKNOWN
License: MIT
Keywords: sandbox docker python
Platform: UNKNOWN
Classifier: Development Status :: 3 - Alpha
Classifier: Intended Audience :: Developers
Classifier: Topic :: Software Development :: Build Tools
Classifier: License :: OSI Approved :: MIT License
Classifier: Programming Language :: Python :: 3
Classifier: Programming Language :: Python :: 3.3
Classifier: Programming Language :: Python :: 3.4
Classifier: Programming Language :: Python :: 3.5
Classifier: Programming Language :: Python :: 3.6
Classifier: Programming Language :: Python :: 3.7
